TCFile/TCFile_class.py
TCFile/__init__.py
tcfile-2024.11.0.dist-info/LICENSE
tcfile-2024.11.0.dist-info/WHEEL
tcfile-2024.11.0.dist-info/METADATA
tcfile-2024.11.0.dist-info/RECORD
