Metadata-Version: 2.3
Name: TCFile
Version: 2024.11.0
Summary: Python package for handling TCF data. It works with Tomcube data
Author-email: Dohyeon Lee <dleh428@kaist.ac.kr>
Maintainer-email: Dohyeon Lee <dleh428@kaist.ac.kr>
Requires-Python: >=3.7,<4
Classifier: Development Status :: 4 - Beta
Classifier: License :: OSI Approved :: MIT License
Classifier: Programming Language :: Python :: 3
Classifier: Topic :: Scientific/Engineering
Requires-Dist: numpy>=1.18.5,<3
Requires-Dist: h5py>=3.2.0,<4
Requires-Dist: pillow>=9.5.0
Requires-Dist: hdf5plugin>=4.4,<5
Requires-Dist: dask
Project-URL: repository, https://github.com/ehgus/TCFile
